aiohttp_i18n/__init__.py
aiohttp_i18n/const.py
aiohttp_i18n/i18n.py
aiohttp_i18n/locale.py
aiohttp_i18n/middleware.py
tests/__init__.py
tests/__test.py
tests/const_test.py
tests/i18n_test.py
tests/locale_test.py
tests/middleware_test.py
aiohttp_i18n-0.0.7.dist-info/METADATA
aiohttp_i18n-0.0.7.dist-info/WHEEL
aiohttp_i18n-0.0.7.dist-info/top_level.txt
aiohttp_i18n-0.0.7.dist-info/RECORD
