Metadata-Version: 2.1
Name: aiohttp-i18n
Version: 0.0.7
Summary: i18n support for aiohttp through babel
Home-page: https://bitbucket.org/mazvv/aiohttp_i18n
Author: Vitalii Mazur
Author-email: vitalii.mazur@gmail.com
License: MIT
Keywords: aiohttp i18n locale babel localization
Platform: POSIX
Classifier: License :: OSI Approved :: MIT License
Classifier: Development Status :: 4 - Beta
Classifier: Programming Language :: Python
Classifier: Programming Language :: Python :: 3
Classifier: Programming Language :: Python :: 3.7
Classifier: Programming Language :: Python :: 3 :: Only
Classifier: Operating System :: POSIX
Classifier: Environment :: Web Environment
Classifier: Intended Audience :: Developers
Classifier: Topic :: Software Development
Classifier: Topic :: Software Development :: Libraries
Classifier: Framework :: AsyncIO
Requires-Python: >=3.7
Requires-Dist: aiohttp (>=3.6.2)
Requires-Dist: babel (>=2.7.0)
Provides-Extra: test
Requires-Dist: mypy (>=0.740) ; extra == 'test'
Requires-Dist: pytest (>=5.3.0) ; extra == 'test'
Requires-Dist: pytest-cov (>=2.8.1) ; extra == 'test'
Requires-Dist: pyfakefs (>=3.6.1) ; extra == 'test'
Requires-Dist: pytest-mock (>=1.12.1) ; extra == 'test'
Requires-Dist: pytest-aiohttp (>=0.3.0) ; extra == 'test'
Requires-Dist: flake8 ; extra == 'test'
